underactuated/__init__.py
underactuated/_static/custom.css
underactuated/conf.py
underactuated/double_integrator.py
underactuated/exercises/acrobot/test_cartpole_balancing.py
underactuated/exercises/acrobot/test_cartpoles_urdf.py
underactuated/exercises/contact/test_compass_gait_limit_cycle.py
underactuated/exercises/dp/J.npy
underactuated/exercises/dp/minimum_time_utils.py
underactuated/exercises/dp/test_lp_dp.py
underactuated/exercises/dp/test_minimum_time.py
underactuated/exercises/dp/test_pendulum_cvi.py
underactuated/exercises/grader.py
underactuated/exercises/humanoids/footstep_planning_gcs_utils.py
underactuated/exercises/humanoids/test_footstep_planning.py
underactuated/exercises/humanoids/test_footstep_planning_gcs.py
underactuated/exercises/intro/test_drake_systems.py
underactuated/exercises/lqr/test_drake_diagrams.py
underactuated/exercises/lyapunov/test_control.py
underactuated/exercises/lyapunov/test_sos_and_psd.py
underactuated/exercises/lyapunov/test_van_der_pol.py
underactuated/exercises/pend/mnist.npz
underactuated/exercises/pend/test_hopfield_network.py
underactuated/exercises/pend/test_vibrating_pendulum.py
underactuated/exercises/planning/test_rrt_planning.py
underactuated/exercises/simple_legs/test_one_d_hopper.py
underactuated/exercises/sysid/test_glider_sysid.py
underactuated/exercises/sysid/test_linear_sysid.py
underactuated/exercises/trajopt/test_ilqr_driving.py
underactuated/exercises/trajopt/test_orbital_transfer.py
underactuated/exercises/trajopt/test_shooting_vs_transcription.py
underactuated/index.md
underactuated/jupyter.py
underactuated/meshcat_cpp_utils.py
underactuated/meshcat_utils.md
underactuated/meshcat_utils.py
underactuated/models/cartpole.urdf
underactuated/models/compass_gait_limit_cycle.urdf
underactuated/models/double_pendulum.sdf
underactuated/models/double_pendulum.urdf
underactuated/models/glider/glider.urdf
underactuated/models/glider/meshes/elevator.obj
underactuated/models/glider/meshes/fuselageh_hstab.obj
underactuated-2025.3.31.dist-info/LICENSE.TXT
underactuated-2025.3.31.dist-info/METADATA
underactuated-2025.3.31.dist-info/WHEEL
underactuated-2025.3.31.dist-info/RECORD
