Metadata-Version: 2.3
Name: underactuated
Version: 2025.3.31
Summary: MIT 6.821 - Underactuated Robotics
License: BSD License
Author: Russ Tedrake
Author-email: russt@mit.edu
Requires-Python: >=3.10,<4.0
Classifier: License :: OSI Approved :: BSD License
Classifier: License :: Other/Proprietary License
Classifier: Programming Language :: Python :: 3
Classifier: Programming Language :: Python :: 3.10
Classifier: Programming Language :: Python :: 3.11
Classifier: Programming Language :: Python :: 3.12
Classifier: Programming Language :: Python :: 3.13
Provides-Extra: all
Provides-Extra: grader
Requires-Dist: drake (>=0.0.20250328,<1.0)
Requires-Dist: gradescope-utils (>=0.4.0) ; extra == "grader" or extra == "all"
Requires-Dist: ipython (>=7.8.0)
Requires-Dist: ipywidgets (>=8)
Requires-Dist: lxml[html-clean] (>=4.9.2) ; extra == "all"
Requires-Dist: matplotlib[mplot3d] (>=3.7.0)
Requires-Dist: mpld3 (>=0.5.1)
Requires-Dist: nbconvert (>=7.0.0) ; extra == "grader" or extra == "all"
Requires-Dist: numpy (>2.0.0)
Requires-Dist: pandas (>=2.0) ; extra == "all"
Requires-Dist: pydot (>=1.3.0)
Requires-Dist: scipy (>=1.10.0) ; extra == "all"
Requires-Dist: timeout-decorator (>=0.4.1) ; extra == "grader" or extra == "all"
